{
    "books": [
        {
            "id": "1",
            "title": "Serpent & Dove",
            "author": "Shelby Mahurin",
            "description": "An Amazon Best Book of 2019 * New York Times Bestseller * B&N's YA Book Club Pick * Indiebound Bestseller * #6 on the 2019 Kids' Indie Next List",
            "price": "ARS$1.472,11",
            "format": "Paperback",
            "language": "English",
            "datePublished": "02 Sep 2020",
            "saga": "Serpent & Dove",
            "image": "https://d1w7fb2mkkr3kw.cloudfront.net/assets/images/book/lrg/9780/0628/9780062878038.jpg"
        },
        {
            "id": "2",
            "title": "Blood & Honey",
            "author": "Shelby Mahurin",
            "description": "The stakes are higher. The witches are deadlier. And the romance is red-hot. The eagerly anticipated sequel to the New York Times and Indiebound bestseller Serpent & Dove is perfect for fans of Sarah J. Maas and is an instant New York Times bestseller!",
            "price": "ARS$2.037,72",
            "format": "Paperback",
            "language": "English",
            "datePublished": "02 Sep 2020",
            "saga": "Serpent & Dove",
            "image": "https://d1w7fb2mkkr3kw.cloudfront.net/assets/images/book/lrg/9780/0630/9780063041172.jpg"
        },
        {
            "id": "3",
            "title": "Gods & Monsters",
            "author": "Shelby Mahurin",
            "description": "",
            "price": "ARS$2.097,07",
            "format": "Paperback",
            "datePublished": "05 Aug 2021",
            "language": "English",
            "image": "https://d1w7fb2mkkr3kw.cloudfront.net/assets/images/book/lrg/9780/0630/9780063038936.jpg"

        },
        {
            "id": "4",
            "title": "The Queen's Gambit",
            "author": "Walter Tevis",
            "description": "NOW A MAJOR NETFLIX SERIES starring Anya Taylor-Joy from Academy-Award nominee Scott Frank and BAFTA nominee Allan Scott",
            "price": "ARS$1.311,34",
            "format": "Paperback",
            "language": "English",
            "datePublished": "14 Apr 2016",
            "image": "https://d1w7fb2mkkr3kw.cloudfront.net/assets/images/book/lrg/9781/4746/9781474600842.jpg"
        },
        {
            "id": "5",
            "title": "The Man Who Fell to Earth",
            "author": "Walter Tevis",
            "description": "NOW A MAJOR NETFLIX SERIES starring Anya Taylor-Joy from Academy-Award nominee Scott Frank and BAFTA nominee Allan Scott",
            "price": "ARS$1.311,34",
            "format": "Paperback",
            "language": "English",
            "datePublished": "14 Apr 2016",
            "image": "https://d1w7fb2mkkr3kw.cloudfront.net/assets/images/book/lrg/9781/4732/9781473213111.jpg"
        },
        {
            "id": "6",
            "title": "1984",
            "author": "George Orwell",
            "description": "Renowned urban artist Shepard Fairey's new look for Orwell's dystopian masterpiece",
            "price": "ARS$1.003,67",
            "format": "Paperback",
            "language": "English",
            "datePublished": "01 Oct 2008",
            "image": "https://d1w7fb2mkkr3kw.cloudfront.net/assets/images/book/lrg/9780/1410/9780141036144.jpg"
        },
        {
            "id": "7",
            "title": "Brave New World",
            "author": "Aldous Huxley",
            "description": "",
            "price": "ARS$1.531,04",
            "format": "Paperback",
            "language": "English",
            "datePublished": "08 Mar 2019",
            "image": "https://d1w7fb2mkkr3kw.cloudfront.net/assets/images/book/lrg/9780/0994/9780099477464.jpg"
        }
    ]
}